buildout.cfg
changes.txt
setup.py
src/ore/__init__.py
src/ore.wsgiapp.egg-info/PKG-INFO
src/ore.wsgiapp.egg-info/SOURCES.txt
src/ore.wsgiapp.egg-info/dependency_links.txt
src/ore.wsgiapp.egg-info/entry_points.txt
src/ore.wsgiapp.egg-info/namespace_packages.txt
src/ore.wsgiapp.egg-info/not-zip-safe
src/ore.wsgiapp.egg-info/requires.txt
src/ore.wsgiapp.egg-info/top_level.txt
src/ore/wsgiapp/README.txt
src/ore/wsgiapp/__init__.py
src/ore/wsgiapp/app.py
src/ore/wsgiapp/configure.zcml
src/ore/wsgiapp/interfaces.py
src/ore/wsgiapp/publication.py
src/ore/wsgiapp/startup.py
src/ore/wsgiapp/test.zcml
src/ore/wsgiapp/tests.py
src/ore/wsgiapp/wsgi.py
