Metadata-Version: 1.0
Name: ore.wsgiapp
Version: 0.3.2
Summary: glue for wsgi zope3 apps w/o zodb
Home-page: UNKNOWN
Author: Kapil Thangavelu
Author-email: kapil.foss@gmail.com
License: ZPL
Platform: UNKNOWN
Classifier: Programming Language :: Python
Classifier: Environment :: Web Environment
Classifier: Topic :: Internet :: WWW/HTTP :: WSGI :: Application
Classifier: Framework :: Zope3
